pymcintosh/__init__.py
pymcintosh/config.py
pymcintosh/const.py
pymcintosh/protocol.py
pymcintosh/protocols/acurus.yaml
pymcintosh/protocols/dayton.yaml
pymcintosh/protocols/monoprice.yaml
pymcintosh/protocols/sonance.yaml
pymcintosh/protocols/xantech.yaml
pymcintosh/protocols/zpr68.yaml
pymcintosh/series/dax88.yaml
pymcintosh/series/monoprice6.yaml
pymcintosh/series/sonance6.yaml
pymcintosh/series/xantech8.yaml
pymcintosh/series/zpr68-10.yaml
pymcintosh-0.0.1.dist-info/LICENSE
pymcintosh-0.0.1.dist-info/METADATA
pymcintosh-0.0.1.dist-info/WHEEL
pymcintosh-0.0.1.dist-info/top_level.txt
pymcintosh-0.0.1.dist-info/zip-safe
pymcintosh-0.0.1.dist-info/RECORD
