Metadata-Version: 2.1
Name: pymcintosh
Version: 0.0.1
Home-page: https://github.com/rsnodgrass/pymcintosh
Download-URL: https://github.com/rsnodgrass/pymcintosh/archive/0.0.1.tar.gz
License: MIT
Classifier: Development Status :: 4 - Beta
Classifier: License :: OSI Approved :: MIT License
Classifier: Programming Language :: Python :: 3
Classifier: Programming Language :: Python :: 3 :: Only
Requires-Python: >=3.10
License-File: LICENSE
Requires-Dist: pyserial >=3.5
Requires-Dist: pyserial-asyncio >=0.5
Provides-Extra: tests
Requires-Dist: pytest ; extra == 'tests'
